{
    "method": "random",
    "metric": {
        "name": "val_loss",
        "goal": "minimize"
    },
    "early_terminate": {
        "type": "hyperband",
        "s": 2,
        "eta": 3,
        "max_iter": 81,
        "min_iter": 5
      },
    "parameters": {
        "lstm_layers": {
            "values": [
                1,
                2,
                3,
                4
            ]
        },
        "dense_layers": {
            "values": [
                1,
                2,
                3
            ]
        },
        "neurons_per_layer": {
            "values": [
                32,
                64,
                128
            ]
        },
        "batch_size": {
            "values": [
                16,
                32,
                64
            ]
        },
        "epochs": {
            "value": 100
        },
        "learning_rate": {
            "values": [
                0.01,
                0.001,
                0.0001,
                0.00001,
                0.0005
            ]
        }
    }
}